reaction/__init__.py
reaction/__version__.py
reaction/rpc/__init__.py
reaction/rpc/base.py
reaction/rpc/common.py
reaction/rpc/rabbitmq.py
reaction-20.2.dist-info/LICENSE
reaction-20.2.dist-info/METADATA
reaction-20.2.dist-info/WHEEL
reaction-20.2.dist-info/top_level.txt
reaction-20.2.dist-info/RECORD
