Metadata-Version: 2.1
Name: reaction
Version: 20.2
Summary: Reaction. ML serving & microservices.
Home-page: https://github.com/catalyst-team/reaction
Author: David Kuryakin
Author-email: dkuryakin@gmail.com
License: Apache License 2.0
Keywords: Machine Learning,Deep Learning,PyTorch
Platform: UNKNOWN
Classifier: License :: OSI Approved :: Apache Software License
Classifier: Intended Audience :: Developers
Classifier: Intended Audience :: Science/Research
Classifier: Programming Language :: Python
Classifier: Programming Language :: Python :: 3.6
Classifier: Programming Language :: Python :: 3.7
Classifier: Programming Language :: Python :: Implementation :: CPython
Classifier: Topic :: Scientific/Engineering :: Artificial Intelligence
Requires-Python: >=3.6.0
Requires-Dist: fastapi[all] (<1.0.0,>=0.38.1)
Requires-Dist: aio-pika (==6.1.1)
